odoo/addons/l10n_nl_postcode/README.rst
odoo/addons/l10n_nl_postcode/__init__.py
odoo/addons/l10n_nl_postcode/__manifest__.py
odoo/addons/l10n_nl_postcode/i18n/l10n_nl_postcode.pot
odoo/addons/l10n_nl_postcode/models/__init__.py
odoo/addons/l10n_nl_postcode/models/res_partner.py
odoo/addons/l10n_nl_postcode/readme/CONTRIBUTORS.rst
odoo/addons/l10n_nl_postcode/readme/DESCRIPTION.rst
odoo/addons/l10n_nl_postcode/readme/INSTALL.rst
odoo/addons/l10n_nl_postcode/readme/USAGE.rst
odoo/addons/l10n_nl_postcode/static/description/icon.png
odoo/addons/l10n_nl_postcode/static/description/index.html
odoo/addons/l10n_nl_postcode/tests/__init__.py
odoo/addons/l10n_nl_postcode/tests/test_l10n_nl_postcode.py
odoo11_addon_l10n_nl_postcode-11.0.1.0.0.99.dev5.dist-info/METADATA
odoo11_addon_l10n_nl_postcode-11.0.1.0.0.99.dev5.dist-info/WHEEL
odoo11_addon_l10n_nl_postcode-11.0.1.0.0.99.dev5.dist-info/top_level.txt
odoo11_addon_l10n_nl_postcode-11.0.1.0.0.99.dev5.dist-info/RECORD
